mongo_exporter/__init__.py
mongo_exporter/tools.py
mongo_exporter-1.6.2.dist-info/METADATA
mongo_exporter-1.6.2.dist-info/WHEEL
mongo_exporter-1.6.2.dist-info/top_level.txt
mongo_exporter-1.6.2.dist-info/RECORD
