Metadata-Version: 2.1
Name: mongo-exporter
Version: 1.6.2
Summary: A tool that supports exporting the database schema from MongoDB.
Author: Alex Haimov
Author-email: haimovalex@gmail.com
Requires-Dist: pymongo
